dbalchemycore/__init__.py
dbalchemycore/core/__init__.py
dbalchemycore/core/config.py
dbalchemycore/core/database.py
dbalchemycore/core/exc.py
dbalchemycore/models/__init__.py
dbalchemycore/models/base_model.py
dbalchemycore/repositories/__init__.py
dbalchemycore/repositories/abstract_repo.py
dbalchemycore-0.1.4.dist-info/licenses/LICENSE
dbalchemycore-0.1.4.dist-info/METADATA
dbalchemycore-0.1.4.dist-info/WHEEL
dbalchemycore-0.1.4.dist-info/top_level.txt
dbalchemycore-0.1.4.dist-info/RECORD
