Metadata-Version: 2.4
Name: dbalchemycore
Version: 0.1.4
Summary: Asynchronous database library using SQLAlchemy Core with CRUD operations
Author-email: tktturik <tktturik@gmail.com>
License: MIT License
Project-URL: Documentation, https://github.com/tktturik/db-alchemy-core
Keywords: database,async,sqlalchemy,postgresql,crud,alembic,pydantic,fastapi
Classifier: Programming Language :: Python :: 3.13
Classifier: License :: OSI Approved :: MIT License
Classifier: Operating System :: OS Independent
Requires-Python: >=3.8
License-File: LICENSE
Requires-Dist: SQLAlchemy==2.0.41
Requires-Dist: pydantic==2.11.7
Requires-Dist: pydantic-core==2.33.2
Requires-Dist: annotated-types==0.7.0
Requires-Dist: asyncpg==0.30.0
Requires-Dist: typing-inspection==0.4.1
Requires-Dist: typing_extensions==4.14.1
Requires-Dist: pydantic-settings==2.5.2
Dynamic: license-file
